liquid2/__about__.py
liquid2/__init__.py
liquid2/ast.py
liquid2/context.py
liquid2/environment.py
liquid2/exceptions.py
liquid2/expression.py
liquid2/filter.py
liquid2/lexer.py
liquid2/limits.py
liquid2/loader.py
liquid2/messages.py
liquid2/output.py
liquid2/parser.py
liquid2/py.typed
liquid2/static_analysis.py
liquid2/stream.py
liquid2/stringify.py
liquid2/tag.py
liquid2/template.py
liquid2/token.py
liquid2/undefined.py
liquid2/unescape.py
liquid2/builtin/__init__.py
liquid2/builtin/comment.py
liquid2/builtin/content.py
liquid2/builtin/expressions.py
liquid2/builtin/output.py
liquid2/builtin/filters/__init__.py
liquid2/builtin/filters/array.py
liquid2/builtin/filters/babel.py
liquid2/builtin/filters/filtering_filters.py
liquid2/builtin/filters/find_filters.py
liquid2/builtin/filters/map_filter.py
liquid2/builtin/filters/math.py
liquid2/builtin/filters/misc.py
liquid2/builtin/filters/sorting_filters.py
liquid2/builtin/filters/string.py
liquid2/builtin/filters/sum_filter.py
liquid2/builtin/filters/translate.py
liquid2/builtin/filters/uniq_filter.py
liquid2/builtin/loaders/__init__.py
liquid2/builtin/loaders/caching_file_system_loader.py
liquid2/builtin/loaders/choice_loader.py
liquid2/builtin/loaders/dict_loader.py
liquid2/builtin/loaders/file_system_loader.py
liquid2/builtin/loaders/mixins.py
liquid2/builtin/loaders/package_loader.py
liquid2/builtin/tags/__init__.py
liquid2/builtin/tags/assign_tag.py
liquid2/builtin/tags/capture_tag.py
liquid2/builtin/tags/case_tag.py
liquid2/builtin/tags/cycle_tag.py
liquid2/builtin/tags/decrement_tag.py
liquid2/builtin/tags/echo_tag.py
liquid2/builtin/tags/extends_tag.py
liquid2/builtin/tags/for_tag.py
liquid2/builtin/tags/if_tag.py
liquid2/builtin/tags/include_tag.py
liquid2/builtin/tags/increment_tag.py
liquid2/builtin/tags/liquid_tag.py
liquid2/builtin/tags/macro_tag.py
liquid2/builtin/tags/raw_tag.py
liquid2/builtin/tags/render_tag.py
liquid2/builtin/tags/translate_tag.py
liquid2/builtin/tags/unless_tag.py
python_liquid2-0.3.0.dist-info/METADATA
python_liquid2-0.3.0.dist-info/WHEEL
python_liquid2-0.3.0.dist-info/licenses/LICENSE.txt
python_liquid2-0.3.0.dist-info/RECORD
