Metadata-Version: 2.4
Name: python-liquid2
Version: 0.3.0
Summary: Liquid templates for Python
Project-URL: Documentation, https://jg-rp.github.io/python-liquid2/
Project-URL: Issues, https://github.com/jg-rp/python-liquid2/issues
Project-URL: Source, https://github.com/jg-rp/python-liquid2
Author-email: James Prior <jamesgr.prior@gmail.com>
License-Expression: MIT
License-File: LICENSE.txt
Classifier: Development Status :: 4 - Beta
Classifier: Intended Audience :: Developers
Classifier: License :: OSI Approved :: MIT License
Classifier: Programming Language :: Python
Classifier: Programming Language :: Python :: 3.10
Classifier: Programming Language :: Python :: 3.11
Classifier: Programming Language :: Python :: 3.12
Classifier: Programming Language :: Python :: 3.13
Classifier: Programming Language :: Python :: Implementation :: CPython
Classifier: Programming Language :: Python :: Implementation :: PyPy
Requires-Python: >=3.10
Requires-Dist: babel>=2
Requires-Dist: markupsafe>=3
Requires-Dist: python-dateutil
Requires-Dist: pytz
Requires-Dist: typing-extensions
